numdatapiyumiyu/__init__.py
numdatapiyumiyu/calculate.py
numdatapiyumiyu-0.0.1.dist-info/LICENSE
numdatapiyumiyu-0.0.1.dist-info/METADATA
numdatapiyumiyu-0.0.1.dist-info/WHEEL
numdatapiyumiyu-0.0.1.dist-info/top_level.txt
numdatapiyumiyu-0.0.1.dist-info/RECORD
